<?xml version="1.0" encoding="UTF-8"?>
<con:soapui-project id="f282fc1d-a131-4e32-8b91-035455b14ee8" activeEnvironment="Default" name="Customer" resourceRoot="" soapui-version="5.5.0" abortOnError="false" runType="SEQUENTIAL" xmlns:con="http://eviware.com/soapui/config"><con:settings/><con:interface xsi:type="con:WsdlInterface" id="e398e6e6-0a8d-435b-8c0f-17be952027de" wsaVersion="NONE" name="customerCustomerRepositoryV1Binding" type="wsdl" bindingName="{http://soap.upskills.in/soap/default?services=customerCustomerRepositoryV1}customerCustomerRepositoryV1Binding" soapVersion="1_2" anonymous="optional" definition="file:/C:/Users/RahulPoddar/Desktop/SDET/SOAP%20API%20WSDL%20EndPoints/customerCustomerRepositoryV1.xml" xmlns:xsi="http://www.w3.org/2001/XMLSchema-instance"><con:settings/><con:definitionCache type="TEXT" rootPart="file:/C:/Users/RahulPoddar/Desktop/SDET/SOAP%20API%20WSDL%20EndPoints/customerCustomerRepositoryV1.xml"><con:part><con:url>file:/C:/Users/RahulPoddar/Desktop/SDET/SOAP%20API%20WSDL%20EndPoints/customerCustomerRepositoryV1.xml</con:url><con:content><![CDATA[<definitions name="MagentoWSDL" targetNamespace="http://soap.upskills.in/soap/default?services=customerCustomerRepositoryV1" xmlns="http://schemas.xmlsoap.org/wsdl/" xmlns:wsdl="http://schemas.xmlsoap.org/wsdl/" xmlns:tns="http://soap.upskills.in/soap/default?services=customerCustomerRepositoryV1" xmlns:soap="http://schemas.xmlsoap.org/wsdl/soap/" xmlns:xsd="http://www.w3.org/2001/XMLSchema" xmlns:soap-enc="http://schemas.xmlsoap.org/soap/encoding/" xmlns:soap12="http://schemas.xmlsoap.org/wsdl/soap12/">
  <types>
    <xsd:schema targetNamespace="http://soap.upskills.in/soap/default?services=customerCustomerRepositoryV1">
      <xsd:element name="GenericFault" type="tns:GenericFault"/>
      <xsd:complexType name="GenericFaultParameter">
        <xsd:sequence>
          <xsd:element name="key" minOccurs="1" maxOccurs="1" type="xsd:string">
            <xsd:annotation>
              <xsd:documentation/>
              <xsd:appinfo xmlns:inf="http://soap.upskills.in/soap/default?services=customerCustomerRepositoryV1">
                <inf:maxLength/>
              </xsd:appinfo>
            </xsd:annotation>
          </xsd:element>
          <xsd:element name="value" minOccurs="1" maxOccurs="1" type="xsd:string">
            <xsd:annotation>
              <xsd:documentation/>
              <xsd:appinfo xmlns:inf="http://soap.upskills.in/soap/default?services=customerCustomerRepositoryV1">
                <inf:maxLength/>
              </xsd:appinfo>
            </xsd:annotation>
          </xsd:element>
        </xsd:sequence>
      </xsd:complexType>
      <xsd:complexType name="ArrayOfGenericFaultParameter">
        <xsd:annotation>
          <xsd:documentation>An array of GenericFaultParameter items.</xsd:documentation>
          <xsd:appinfo xmlns:inf="http://soap.upskills.in/soap/default?services=customerCustomerRepositoryV1"/>
        </xsd:annotation>
        <xsd:sequence>
          <xsd:element name="item" minOccurs="0" maxOccurs="unbounded" type="tns:GenericFaultParameter">
            <xsd:annotation>
              <xsd:documentation>An item of ArrayOfGenericFaultParameter.</xsd:documentation>
              <xsd:appinfo xmlns:inf="http://soap.upskills.in/soap/default?services=customerCustomerRepositoryV1"/>
            </xsd:annotation>
          </xsd:element>
        </xsd:sequence>
      </xsd:complexType>
      <xsd:complexType name="WrappedError">
        <xsd:sequence>
          <xsd:element name="message" minOccurs="1" maxOccurs="1" type="xsd:string">
            <xsd:annotation>
              <xsd:documentation/>
              <xsd:appinfo xmlns:inf="http://soap.upskills.in/soap/default?services=customerCustomerRepositoryV1">
                <inf:maxLength/>
              </xsd:appinfo>
            </xsd:annotation>
          </xsd:element>
          <xsd:element name="parameters" type="tns:ArrayOfGenericFaultParameter" minOccurs="0">
            <xsd:annotation>
              <xsd:documentation>Message parameters.</xsd:documentation>
              <xsd:appinfo xmlns:inf="http://soap.upskills.in/soap/default?services=customerCustomerRepositoryV1">
                <inf:natureOfType>array</inf:natureOfType>
              </xsd:appinfo>
            </xsd:annotation>
          </xsd:element>
        </xsd:sequence>
      </xsd:complexType>
      <xsd:complexType name="ArrayOfWrappedError">
        <xsd:annotation>
          <xsd:documentation>An array of WrappedError items.</xsd:documentation>
          <xsd:appinfo xmlns:inf="http://soap.upskills.in/soap/default?services=customerCustomerRepositoryV1"/>
        </xsd:annotation>
        <xsd:sequence>
          <xsd:element name="item" minOccurs="0" maxOccurs="unbounded" type="tns:WrappedError">
            <xsd:annotation>
              <xsd:documentation>An item of ArrayOfWrappedError.</xsd:documentation>
              <xsd:appinfo xmlns:inf="http://soap.upskills.in/soap/default?services=customerCustomerRepositoryV1"/>
            </xsd:annotation>
          </xsd:element>
        </xsd:sequence>
      </xsd:complexType>
      <xsd:complexType name="GenericFault">
        <xsd:sequence>
          <xsd:element name="Trace" minOccurs="0" maxOccurs="1" type="xsd:string">
            <xsd:annotation>
              <xsd:documentation>Exception calls stack trace.</xsd:documentation>
              <xsd:appinfo xmlns:inf="http://soap.upskills.in/soap/default?services=customerCustomerRepositoryV1">
                <inf:maxLength/>
              </xsd:appinfo>
            </xsd:annotation>
          </xsd:element>
          <xsd:element name="Parameters" type="tns:ArrayOfGenericFaultParameter" minOccurs="0">
            <xsd:annotation>
              <xsd:documentation>Additional exception parameters.</xsd:documentation>
              <xsd:appinfo xmlns:inf="http://soap.upskills.in/soap/default?services=customerCustomerRepositoryV1">
                <inf:natureOfType>array</inf:natureOfType>
              </xsd:appinfo>
            </xsd:annotation>
          </xsd:element>
          <xsd:element name="WrappedErrors" type="tns:ArrayOfWrappedError" minOccurs="0">
            <xsd:annotation>
              <xsd:documentation>Additional wrapped errors.</xsd:documentation>
              <xsd:appinfo xmlns:inf="http://soap.upskills.in/soap/default?services=customerCustomerRepositoryV1">
                <inf:natureOfType>array</inf:natureOfType>
              </xsd:appinfo>
            </xsd:annotation>
          </xsd:element>
        </xsd:sequence>
      </xsd:complexType>
      <xsd:complexType name="FrameworkDataImageContentInterface">
        <xsd:annotation>
          <xsd:documentation>Image Content data interface</xsd:documentation>
          <xsd:appinfo xmlns:inf="http://soap.upskills.in/soap/default?services=customerCustomerRepositoryV1"/>
        </xsd:annotation>
        <xsd:sequence>
          <xsd:element name="base64EncodedData" minOccurs="1" maxOccurs="1" type="xsd:string">
            <xsd:annotation>
              <xsd:documentation>Media data (base64 encoded content)</xsd:documentation>
              <xsd:appinfo xmlns:inf="http://soap.upskills.in/soap/default?services=customerCustomerRepositoryV1">
                <inf:maxLength/>
              </xsd:appinfo>
            </xsd:annotation>
          </xsd:element>
          <xsd:element name="type" minOccurs="1" maxOccurs="1" type="xsd:string">
            <xsd:annotation>
              <xsd:documentation>MIME type</xsd:documentation>
              <xsd:appinfo xmlns:inf="http://soap.upskills.in/soap/default?services=customerCustomerRepositoryV1">
                <inf:maxLength/>
              </xsd:appinfo>
            </xsd:annotation>
          </xsd:element>
          <xsd:element name="name" minOccurs="1" maxOccurs="1" type="xsd:string">
            <xsd:annotation>
              <xsd:documentation>Image name</xsd:documentation>
              <xsd:appinfo xmlns:inf="http://soap.upskills.in/soap/default?services=customerCustomerRepositoryV1">
                <inf:maxLength/>
              </xsd:appinfo>
            </xsd:annotation>
          </xsd:element>
        </xsd:sequence>
      </xsd:complexType>
      <xsd:complexType name="CustomerDataRegionExtensionInterface">
        <xsd:annotation>
          <xsd:documentation>ExtensionInterface class for @see \Magento\Customer\Api\Data\RegionInterface</xsd:documentation>
          <xsd:appinfo xmlns:inf="http://soap.upskills.in/soap/default?services=customerCustomerRepositoryV1"/>
        </xsd:annotation>
      </xsd:complexType>
      <xsd:complexType name="CustomerDataRegionInterface">
        <xsd:annotation>
          <xsd:documentation>Customer address region interface.</xsd:documentation>
          <xsd:appinfo xmlns:inf="http://soap.upskills.in/soap/default?services=customerCustomerRepositoryV1"/>
        </xsd:annotation>
        <xsd:sequence>
          <xsd:element name="regionCode" minOccurs="1" maxOccurs="1" type="xsd:string">
            <xsd:annotation>
              <xsd:documentation>Region code</xsd:documentation>
              <xsd:appinfo xmlns:inf="http://soap.upskills.in/soap/default?services=customerCustomerRepositoryV1">
                <inf:maxLength/>
              </xsd:appinfo>
            </xsd:annotation>
          </xsd:element>
          <xsd:element name="region" minOccurs="1" maxOccurs="1" type="xsd:string">
            <xsd:annotation>
              <xsd:documentation>Region</xsd:documentation>
              <xsd:appinfo xmlns:inf="http://soap.upskills.in/soap/default?services=customerCustomerRepositoryV1">
                <inf:maxLength/>
              </xsd:appinfo>
            </xsd:annotation>
          </xsd:element>
          <xsd:element name="regionId" minOccurs="1" maxOccurs="1" type="xsd:int">
            <xsd:annotation>
              <xsd:documentation>Region id</xsd:documentation>
              <xsd:appinfo xmlns:inf="http://soap.upskills.in/soap/default?services=customerCustomerRepositoryV1">
                <inf:min/>
                <inf:max/>
              </xsd:appinfo>
            </xsd:annotation>
          </xsd:element>
          <xsd:element name="extensionAttributes" minOccurs="0" maxOccurs="1" type="tns:CustomerDataRegionExtensionInterface">
            <xsd:annotation>
              <xsd:documentation>Existing extension attributes object or create a new one.</xsd:documentation>
              <xsd:appinfo xmlns:inf="http://soap.upskills.in/soap/default?services=customerCustomerRepositoryV1"/>
            </xsd:annotation>
          </xsd:element>
        </xsd:sequence>
      </xsd:complexType>
      <xsd:complexType name="ArrayOfString">
        <xsd:annotation>
          <xsd:documentation>An array of string items.</xsd:documentation>
          <xsd:appinfo xmlns:inf="http://soap.upskills.in/soap/default?services=customerCustomerRepositoryV1"/>
        </xsd:annotation>
        <xsd:sequence>
          <xsd:element name="item" minOccurs="0" maxOccurs="unbounded" type="xsd:string">
            <xsd:annotation>
              <xsd:documentation>An item of ArrayOfString.</xsd:documentation>
              <xsd:appinfo xmlns:inf="http://soap.upskills.in/soap/default?services=customerCustomerRepositoryV1">
                <inf:maxLength/>
              </xsd:appinfo>
            </xsd:annotation>
          </xsd:element>
        </xsd:sequence>
      </xsd:complexType>
      <xsd:complexType name="CustomerDataAddressExtensionInterface">
        <xsd:annotation>
          <xsd:documentation>ExtensionInterface class for @see \Magento\Customer\Api\Data\AddressInterface</xsd:documentation>
          <xsd:appinfo xmlns:inf="http://soap.upskills.in/soap/default?services=customerCustomerRepositoryV1"/>
        </xsd:annotation>
      </xsd:complexType>
      <xsd:complexType name="FrameworkAttributeInterface">
        <xsd:annotation>
          <xsd:documentation>Interface for custom attribute value.</xsd:documentation>
          <xsd:appinfo xmlns:inf="http://soap.upskills.in/soap/default?services=customerCustomerRepositoryV1"/>
        </xsd:annotation>
        <xsd:sequence>
          <xsd:element name="attributeCode" minOccurs="1" maxOccurs="1" type="xsd:string">
            <xsd:annotation>
              <xsd:documentation>Attribute code</xsd:documentation>
              <xsd:appinfo xmlns:inf="http://soap.upskills.in/soap/default?services=customerCustomerRepositoryV1">
                <inf:maxLength/>
              </xsd:appinfo>
            </xsd:annotation>
          </xsd:element>
          <xsd:element name="value" minOccurs="1" maxOccurs="1" type="xsd:anyType">
            <xsd:annotation>
              <xsd:documentation>Attribute value</xsd:documentation>
              <xsd:appinfo xmlns:inf="http://soap.upskills.in/soap/default?services=customerCustomerRepositoryV1"/>
            </xsd:annotation>
          </xsd:element>
        </xsd:sequence>
      </xsd:complexType>
      <xsd:complexType name="ArrayOfFrameworkAttributeInterface">
        <xsd:annotation>
          <xsd:documentation>An array of FrameworkAttributeInterface items.</xsd:documentation>
          <xsd:appinfo xmlns:inf="http://soap.upskills.in/soap/default?services=customerCustomerRepositoryV1"/>
        </xsd:annotation>
        <xsd:sequence>
          <xsd:element name="item" minOccurs="0" maxOccurs="unbounded" type="tns:FrameworkAttributeInterface">
            <xsd:annotation>
              <xsd:documentation>An item of ArrayOfFrameworkAttributeInterface.</xsd:documentation>
              <xsd:appinfo xmlns:inf="http://soap.upskills.in/soap/default?services=customerCustomerRepositoryV1"/>
            </xsd:annotation>
          </xsd:element>
        </xsd:sequence>
      </xsd:complexType>
      <xsd:complexType name="CustomerDataAddressInterface">
        <xsd:annotation>
          <xsd:documentation>Customer address interface.</xsd:documentation>
          <xsd:appinfo xmlns:inf="http://soap.upskills.in/soap/default?services=customerCustomerRepositoryV1"/>
        </xsd:annotation>
        <xsd:sequence>
          <xsd:element name="id" minOccurs="0" maxOccurs="1" type="xsd:int">
            <xsd:annotation>
              <xsd:documentation>ID</xsd:documentation>
              <xsd:appinfo xmlns:inf="http://soap.upskills.in/soap/default?services=customerCustomerRepositoryV1">
                <inf:min/>
                <inf:max/>
              </xsd:appinfo>
            </xsd:annotation>
          </xsd:element>
          <xsd:element name="customerId" minOccurs="0" maxOccurs="1" type="xsd:int">
            <xsd:annotation>
              <xsd:documentation>Customer ID</xsd:documentation>
              <xsd:appinfo xmlns:inf="http://soap.upskills.in/soap/default?services=customerCustomerRepositoryV1">
                <inf:min/>
                <inf:max/>
              </xsd:appinfo>
            </xsd:annotation>
          </xsd:element>
          <xsd:element name="region" minOccurs="0" maxOccurs="1" type="tns:CustomerDataRegionInterface">
            <xsd:annotation>
              <xsd:documentation>Region</xsd:documentation>
              <xsd:appinfo xmlns:inf="http://soap.upskills.in/soap/default?services=customerCustomerRepositoryV1"/>
            </xsd:annotation>
          </xsd:element>
          <xsd:element name="regionId" minOccurs="0" maxOccurs="1" type="xsd:int">
            <xsd:annotation>
              <xsd:documentation>Region ID</xsd:documentation>
              <xsd:appinfo xmlns:inf="http://soap.upskills.in/soap/default?services=customerCustomerRepositoryV1">
                <inf:min/>
                <inf:max/>
              </xsd:appinfo>
            </xsd:annotation>
          </xsd:element>
          <xsd:element name="countryId" minOccurs="0" maxOccurs="1" type="xsd:string">
            <xsd:annotation>
              <xsd:documentation>Country code in ISO_3166-2 format</xsd:documentation>
              <xsd:appinfo xmlns:inf="http://soap.upskills.in/soap/default?services=customerCustomerRepositoryV1">
                <inf:maxLength/>
              </xsd:appinfo>
            </xsd:annotation>
          </xsd:element>
          <xsd:element name="street" type="tns:ArrayOfString" minOccurs="0">
            <xsd:annotation>
              <xsd:documentation>Street</xsd:documentation>
              <xsd:appinfo xmlns:inf="http://soap.upskills.in/soap/default?services=customerCustomerRepositoryV1">
                <inf:natureOfType>array</inf:natureOfType>
              </xsd:appinfo>
            </xsd:annotation>
          </xsd:element>
          <xsd:element name="company" minOccurs="0" maxOccurs="1" type="xsd:string">
            <xsd:annotation>
              <xsd:documentation>Company</xsd:documentation>
              <xsd:appinfo xmlns:inf="http://soap.upskills.in/soap/default?services=customerCustomerRepositoryV1">
                <inf:maxLength/>
              </xsd:appinfo>
            </xsd:annotation>
          </xsd:element>
          <xsd:element name="telephone" minOccurs="0" maxOccurs="1" type="xsd:string">
            <xsd:annotation>
              <xsd:documentation>Telephone number</xsd:documentation>
              <xsd:appinfo xmlns:inf="http://soap.upskills.in/soap/default?services=customerCustomerRepositoryV1">
                <inf:maxLength/>
              </xsd:appinfo>
            </xsd:annotation>
          </xsd:element>
          <xsd:element name="fax" minOccurs="0" maxOccurs="1" type="xsd:string">
            <xsd:annotation>
              <xsd:documentation>Fax number</xsd:documentation>
              <xsd:appinfo xmlns:inf="http://soap.upskills.in/soap/default?services=customerCustomerRepositoryV1">
                <inf:maxLength/>
              </xsd:appinfo>
            </xsd:annotation>
          </xsd:element>
          <xsd:element name="postcode" minOccurs="0" maxOccurs="1" type="xsd:string">
            <xsd:annotation>
              <xsd:documentation>Postcode</xsd:documentation>
              <xsd:appinfo xmlns:inf="http://soap.upskills.in/soap/default?services=customerCustomerRepositoryV1">
                <inf:maxLength/>
              </xsd:appinfo>
            </xsd:annotation>
          </xsd:element>
          <xsd:element name="city" minOccurs="0" maxOccurs="1" type="xsd:string">
            <xsd:annotation>
              <xsd:documentation>City name</xsd:documentation>
              <xsd:appinfo xmlns:inf="http://soap.upskills.in/soap/default?services=customerCustomerRepositoryV1">
                <inf:maxLength/>
              </xsd:appinfo>
            </xsd:annotation>
          </xsd:element>
          <xsd:element name="firstname" minOccurs="0" maxOccurs="1" type="xsd:string">
            <xsd:annotation>
              <xsd:documentation>First name</xsd:documentation>
              <xsd:appinfo xmlns:inf="http://soap.upskills.in/soap/default?services=customerCustomerRepositoryV1">
                <inf:maxLength/>
              </xsd:appinfo>
            </xsd:annotation>
          </xsd:element>
          <xsd:element name="lastname" minOccurs="0" maxOccurs="1" type="xsd:string">
            <xsd:annotation>
              <xsd:documentation>Last name</xsd:documentation>
              <xsd:appinfo xmlns:inf="http://soap.upskills.in/soap/default?services=customerCustomerRepositoryV1">
                <inf:maxLength/>
              </xsd:appinfo>
            </xsd:annotation>
          </xsd:element>
          <xsd:element name="middlename" minOccurs="0" maxOccurs="1" type="xsd:string">
            <xsd:annotation>
              <xsd:documentation>Middle name</xsd:documentation>
              <xsd:appinfo xmlns:inf="http://soap.upskills.in/soap/default?services=customerCustomerRepositoryV1">
                <inf:maxLength/>
              </xsd:appinfo>
            </xsd:annotation>
          </xsd:element>
          <xsd:element name="prefix" minOccurs="0" maxOccurs="1" type="xsd:string">
            <xsd:annotation>
              <xsd:documentation>Prefix</xsd:documentation>
              <xsd:appinfo xmlns:inf="http://soap.upskills.in/soap/default?services=customerCustomerRepositoryV1">
                <inf:maxLength/>
              </xsd:appinfo>
            </xsd:annotation>
          </xsd:element>
          <xsd:element name="suffix" minOccurs="0" maxOccurs="1" type="xsd:string">
            <xsd:annotation>
              <xsd:documentation>Suffix</xsd:documentation>
              <xsd:appinfo xmlns:inf="http://soap.upskills.in/soap/default?services=customerCustomerRepositoryV1">
                <inf:maxLength/>
              </xsd:appinfo>
            </xsd:annotation>
          </xsd:element>
          <xsd:element name="vatId" minOccurs="0" maxOccurs="1" type="xsd:string">
            <xsd:annotation>
              <xsd:documentation>Vat id</xsd:documentation>
              <xsd:appinfo xmlns:inf="http://soap.upskills.in/soap/default?services=customerCustomerRepositoryV1">
                <inf:maxLength/>
              </xsd:appinfo>
            </xsd:annotation>
          </xsd:element>
          <xsd:element name="defaultShipping" minOccurs="0" maxOccurs="1" type="xsd:boolean">
            <xsd:annotation>
              <xsd:documentation>If this address is default shipping address.</xsd:documentation>
              <xsd:appinfo xmlns:inf="http://soap.upskills.in/soap/default?services=customerCustomerRepositoryV1">
                <inf:default>false</inf:default>
              </xsd:appinfo>
            </xsd:annotation>
          </xsd:element>
          <xsd:element name="defaultBilling" minOccurs="0" maxOccurs="1" type="xsd:boolean">
            <xsd:annotation>
              <xsd:documentation>If this address is default billing address</xsd:documentation>
              <xsd:appinfo xmlns:inf="http://soap.upskills.in/soap/default?services=customerCustomerRepositoryV1">
                <inf:default>false</inf:default>
              </xsd:appinfo>
            </xsd:annotation>
          </xsd:element>
          <xsd:element name="extensionAttributes" minOccurs="0" maxOccurs="1" type="tns:CustomerDataAddressExtensionInterface">
            <xsd:annotation>
              <xsd:documentation>Existing extension attributes object or create a new one.</xsd:documentation>
              <xsd:appinfo xmlns:inf="http://soap.upskills.in/soap/default?services=customerCustomerRepositoryV1"/>
            </xsd:annotation>
          </xsd:element>
          <xsd:element name="customAttributes" type="tns:ArrayOfFrameworkAttributeInterface" minOccurs="0">
            <xsd:annotation>
              <xsd:documentation>Custom attributes values.</xsd:documentation>
              <xsd:appinfo xmlns:inf="http://soap.upskills.in/soap/default?services=customerCustomerRepositoryV1">
                <inf:natureOfType>array</inf:natureOfType>
              </xsd:appinfo>
            </xsd:annotation>
          </xsd:element>
        </xsd:sequence>
      </xsd:complexType>
      <xsd:element name="customerCustomerRepositoryV1GetByIdRequest" type="tns:CustomerCustomerRepositoryV1GetByIdRequest"/>
      <xsd:complexType name="CustomerCustomerRepositoryV1GetByIdRequest">
        <xsd:annotation>
          <xsd:documentation>Get customer by Customer ID.</xsd:documentation>
          <xsd:appinfo xmlns:inf="http://soap.upskills.in/soap/default?services=customerCustomerRepositoryV1"/>
        </xsd:annotation>
        <xsd:sequence>
          <xsd:element name="customerId" minOccurs="1" maxOccurs="1" type="xsd:int">
            <xsd:annotation>
              <xsd:documentation/>
              <xsd:appinfo xmlns:inf="http://soap.upskills.in/soap/default?services=customerCustomerRepositoryV1">
                <inf:min/>
                <inf:max/>
                <inf:callInfo>
                  <inf:callName>customerCustomerRepositoryV1GetById</inf:callName>
                  <inf:requiredInput>Yes</inf:requiredInput>
                </inf:callInfo>
              </xsd:appinfo>
            </xsd:annotation>
          </xsd:element>
        </xsd:sequence>
      </xsd:complexType>
      <xsd:element name="customerCustomerRepositoryV1GetByIdResponse" type="tns:CustomerCustomerRepositoryV1GetByIdResponse"/>
      <xsd:complexType name="ArrayOfCustomerDataAddressInterface">
        <xsd:annotation>
          <xsd:documentation>An array of CustomerDataAddressInterface items.</xsd:documentation>
          <xsd:appinfo xmlns:inf="http://soap.upskills.in/soap/default?services=customerCustomerRepositoryV1"/>
        </xsd:annotation>
        <xsd:sequence>
          <xsd:element name="item" minOccurs="0" maxOccurs="unbounded" type="tns:CustomerDataAddressInterface">
            <xsd:annotation>
              <xsd:documentation>An item of ArrayOfCustomerDataAddressInterface.</xsd:documentation>
              <xsd:appinfo xmlns:inf="http://soap.upskills.in/soap/default?services=customerCustomerRepositoryV1">
                <inf:callInfo>
                  <inf:callName>customerCustomerRepositoryV1GetById</inf:callName>
                  <inf:callName>customerCustomerRepositoryV1Save</inf:callName>
                  <inf:returned>Conditionally</inf:returned>
                </inf:callInfo>
                <inf:callInfo>
                  <inf:callName>customerCustomerRepositoryV1Save</inf:callName>
                  <inf:requiredInput>No</inf:requiredInput>
                </inf:callInfo>
              </xsd:appinfo>
            </xsd:annotation>
          </xsd:element>
        </xsd:sequence>
      </xsd:complexType>
      <xsd:complexType name="CustomerDataCustomerExtensionInterface">
        <xsd:annotation>
          <xsd:documentation>ExtensionInterface class for @see \Magento\Customer\Api\Data\CustomerInterface</xsd:documentation>
          <xsd:appinfo xmlns:inf="http://soap.upskills.in/soap/default?services=customerCustomerRepositoryV1"/>
        </xsd:annotation>
        <xsd:sequence>
          <xsd:element name="isSubscribed" minOccurs="0" maxOccurs="1" type="xsd:boolean">
            <xsd:annotation>
              <xsd:documentation/>
              <xsd:appinfo xmlns:inf="http://soap.upskills.in/soap/default?services=customerCustomerRepositoryV1">
                <inf:default>false</inf:default>
                <inf:callInfo>
                  <inf:callName>customerCustomerRepositoryV1GetById</inf:callName>
                  <inf:callName>customerCustomerRepositoryV1Save</inf:callName>
                  <inf:returned>Conditionally</inf:returned>
                </inf:callInfo>
                <inf:callInfo>
                  <inf:callName>customerCustomerRepositoryV1Save</inf:callName>
                  <inf:requiredInput>No</inf:requiredInput>
                </inf:callInfo>
              </xsd:appinfo>
            </xsd:annotation>
          </xsd:element>
          <xsd:element name="amazonId" minOccurs="0" maxOccurs="1" type="xsd:string">
            <xsd:annotation>
              <xsd:documentation/>
              <xsd:appinfo xmlns:inf="http://soap.upskills.in/soap/default?services=customerCustomerRepositoryV1">
                <inf:maxLength/>
                <inf:callInfo>
                  <inf:callName>customerCustomerRepositoryV1GetById</inf:callName>
                  <inf:callName>customerCustomerRepositoryV1Save</inf:callName>
                  <inf:returned>Conditionally</inf:returned>
                </inf:callInfo>
                <inf:callInfo>
                  <inf:callName>customerCustomerRepositoryV1Save</inf:callName>
                  <inf:requiredInput>No</inf:requiredInput>
                </inf:callInfo>
              </xsd:appinfo>
            </xsd:annotation>
          </xsd:element>
          <xsd:element name="vertexCustomerCode" minOccurs="0" maxOccurs="1" type="xsd:string">
            <xsd:annotation>
              <xsd:documentation/>
              <xsd:appinfo xmlns:inf="http://soap.upskills.in/soap/default?services=customerCustomerRepositoryV1">
                <inf:maxLength/>
                <inf:callInfo>
                  <inf:callName>customerCustomerRepositoryV1GetById</inf:callName>
                  <inf:callName>customerCustomerRepositoryV1Save</inf:callName>
                  <inf:returned>Conditionally</inf:returned>
                </inf:callInfo>
                <inf:callInfo>
                  <inf:callName>customerCustomerRepositoryV1Save</inf:callName>
                  <inf:requiredInput>No</inf:requiredInput>
                </inf:callInfo>
              </xsd:appinfo>
            </xsd:annotation>
          </xsd:element>
        </xsd:sequence>
      </xsd:complexType>
      <xsd:complexType name="CustomerDataCustomerInterface">
        <xsd:annotation>
          <xsd:documentation>Customer interface.</xsd:documentation>
          <xsd:appinfo xmlns:inf="http://soap.upskills.in/soap/default?services=customerCustomerRepositoryV1"/>
        </xsd:annotation>
        <xsd:sequence>
          <xsd:element name="id" minOccurs="0" maxOccurs="1" type="xsd:int">
            <xsd:annotation>
              <xsd:documentation>Customer id</xsd:documentation>
              <xsd:appinfo xmlns:inf="http://soap.upskills.in/soap/default?services=customerCustomerRepositoryV1">
                <inf:min/>
                <inf:max/>
                <inf:callInfo>
                  <inf:callName>customerCustomerRepositoryV1GetById</inf:callName>
                  <inf:callName>customerCustomerRepositoryV1Save</inf:callName>
                  <inf:returned>Conditionally</inf:returned>
                </inf:callInfo>
                <inf:callInfo>
                  <inf:callName>customerCustomerRepositoryV1Save</inf:callName>
                  <inf:requiredInput>No</inf:requiredInput>
                </inf:callInfo>
              </xsd:appinfo>
            </xsd:annotation>
          </xsd:element>
          <xsd:element name="groupId" minOccurs="0" maxOccurs="1" type="xsd:int">
            <xsd:annotation>
              <xsd:documentation>Group id</xsd:documentation>
              <xsd:appinfo xmlns:inf="http://soap.upskills.in/soap/default?services=customerCustomerRepositoryV1">
                <inf:min/>
                <inf:max/>
                <inf:callInfo>
                  <inf:callName>customerCustomerRepositoryV1GetById</inf:callName>
                  <inf:callName>customerCustomerRepositoryV1Save</inf:callName>
                  <inf:returned>Conditionally</inf:returned>
                </inf:callInfo>
                <inf:callInfo>
                  <inf:callName>customerCustomerRepositoryV1Save</inf:callName>
                  <inf:requiredInput>No</inf:requiredInput>
                </inf:callInfo>
              </xsd:appinfo>
            </xsd:annotation>
          </xsd:element>
          <xsd:element name="defaultBilling" minOccurs="0" maxOccurs="1" type="xsd:string">
            <xsd:annotation>
              <xsd:documentation>Default billing address id</xsd:documentation>
              <xsd:appinfo xmlns:inf="http://soap.upskills.in/soap/default?services=customerCustomerRepositoryV1">
                <inf:maxLength/>
                <inf:callInfo>
                  <inf:callName>customerCustomerRepositoryV1GetById</inf:callName>
                  <inf:callName>customerCustomerRepositoryV1Save</inf:callName>
                  <inf:returned>Conditionally</inf:returned>
                </inf:callInfo>
                <inf:callInfo>
                  <inf:callName>customerCustomerRepositoryV1Save</inf:callName>
                  <inf:requiredInput>No</inf:requiredInput>
                </inf:callInfo>
              </xsd:appinfo>
            </xsd:annotation>
          </xsd:element>
          <xsd:element name="defaultShipping" minOccurs="0" maxOccurs="1" type="xsd:string">
            <xsd:annotation>
              <xsd:documentation>Default shipping address id</xsd:documentation>
              <xsd:appinfo xmlns:inf="http://soap.upskills.in/soap/default?services=customerCustomerRepositoryV1">
                <inf:maxLength/>
                <inf:callInfo>
                  <inf:callName>customerCustomerRepositoryV1GetById</inf:callName>
                  <inf:callName>customerCustomerRepositoryV1Save</inf:callName>
                  <inf:returned>Conditionally</inf:returned>
                </inf:callInfo>
                <inf:callInfo>
                  <inf:callName>customerCustomerRepositoryV1Save</inf:callName>
                  <inf:requiredInput>No</inf:requiredInput>
                </inf:callInfo>
              </xsd:appinfo>
            </xsd:annotation>
          </xsd:element>
          <xsd:element name="confirmation" minOccurs="0" maxOccurs="1" type="xsd:string">
            <xsd:annotation>
              <xsd:documentation>Confirmation</xsd:documentation>
              <xsd:appinfo xmlns:inf="http://soap.upskills.in/soap/default?services=customerCustomerRepositoryV1">
                <inf:maxLength/>
                <inf:callInfo>
                  <inf:callName>customerCustomerRepositoryV1GetById</inf:callName>
                  <inf:callName>customerCustomerRepositoryV1Save</inf:callName>
                  <inf:returned>Conditionally</inf:returned>
                </inf:callInfo>
                <inf:callInfo>
                  <inf:callName>customerCustomerRepositoryV1Save</inf:callName>
                  <inf:requiredInput>No</inf:requiredInput>
                </inf:callInfo>
              </xsd:appinfo>
            </xsd:annotation>
          </xsd:element>
          <xsd:element name="createdAt" minOccurs="0" maxOccurs="1" type="xsd:string">
            <xsd:annotation>
              <xsd:documentation>Created at time</xsd:documentation>
              <xsd:appinfo xmlns:inf="http://soap.upskills.in/soap/default?services=customerCustomerRepositoryV1">
                <inf:maxLength/>
                <inf:callInfo>
                  <inf:callName>customerCustomerRepositoryV1GetById</inf:callName>
                  <inf:callName>customerCustomerRepositoryV1Save</inf:callName>
                  <inf:returned>Conditionally</inf:returned>
                </inf:callInfo>
                <inf:callInfo>
                  <inf:callName>customerCustomerRepositoryV1Save</inf:callName>
                  <inf:requiredInput>No</inf:requiredInput>
                </inf:callInfo>
              </xsd:appinfo>
            </xsd:annotation>
          </xsd:element>
          <xsd:element name="updatedAt" minOccurs="0" maxOccurs="1" type="xsd:string">
            <xsd:annotation>
              <xsd:documentation>Updated at time</xsd:documentation>
              <xsd:appinfo xmlns:inf="http://soap.upskills.in/soap/default?services=customerCustomerRepositoryV1">
                <inf:maxLength/>
                <inf:callInfo>
                  <inf:callName>customerCustomerRepositoryV1GetById</inf:callName>
                  <inf:callName>customerCustomerRepositoryV1Save</inf:callName>
                  <inf:returned>Conditionally</inf:returned>
                </inf:callInfo>
                <inf:callInfo>
                  <inf:callName>customerCustomerRepositoryV1Save</inf:callName>
                  <inf:requiredInput>No</inf:requiredInput>
                </inf:callInfo>
              </xsd:appinfo>
            </xsd:annotation>
          </xsd:element>
          <xsd:element name="createdIn" minOccurs="0" maxOccurs="1" type="xsd:string">
            <xsd:annotation>
              <xsd:documentation>Created in area</xsd:documentation>
              <xsd:appinfo xmlns:inf="http://soap.upskills.in/soap/default?services=customerCustomerRepositoryV1">
                <inf:maxLength/>
                <inf:callInfo>
                  <inf:callName>customerCustomerRepositoryV1GetById</inf:callName>
                  <inf:callName>customerCustomerRepositoryV1Save</inf:callName>
                  <inf:returned>Conditionally</inf:returned>
                </inf:callInfo>
                <inf:callInfo>
                  <inf:callName>customerCustomerRepositoryV1Save</inf:callName>
                  <inf:requiredInput>No</inf:requiredInput>
                </inf:callInfo>
              </xsd:appinfo>
            </xsd:annotation>
          </xsd:element>
          <xsd:element name="dob" minOccurs="0" maxOccurs="1" type="xsd:string">
            <xsd:annotation>
              <xsd:documentation>Date of birth</xsd:documentation>
              <xsd:appinfo xmlns:inf="http://soap.upskills.in/soap/default?services=customerCustomerRepositoryV1">
                <inf:maxLength/>
                <inf:callInfo>
                  <inf:callName>customerCustomerRepositoryV1GetById</inf:callName>
                  <inf:callName>customerCustomerRepositoryV1Save</inf:callName>
                  <inf:returned>Conditionally</inf:returned>
                </inf:callInfo>
                <inf:callInfo>
                  <inf:callName>customerCustomerRepositoryV1Save</inf:callName>
                  <inf:requiredInput>No</inf:requiredInput>
                </inf:callInfo>
              </xsd:appinfo>
            </xsd:annotation>
          </xsd:element>
          <xsd:element name="email" minOccurs="1" maxOccurs="1" type="xsd:string">
            <xsd:annotation>
              <xsd:documentation>Email address</xsd:documentation>
              <xsd:appinfo xmlns:inf="http://soap.upskills.in/soap/default?services=customerCustomerRepositoryV1">
                <inf:maxLength/>
                <inf:callInfo>
                  <inf:callName>customerCustomerRepositoryV1GetById</inf:callName>
                  <inf:callName>customerCustomerRepositoryV1Save</inf:callName>
                  <inf:returned>Conditionally</inf:returned>
                </inf:callInfo>
                <inf:callInfo>
                  <inf:callName>customerCustomerRepositoryV1Save</inf:callName>
                  <inf:requiredInput>No</inf:requiredInput>
                </inf:callInfo>
              </xsd:appinfo>
            </xsd:annotation>
          </xsd:element>
          <xsd:element name="firstname" minOccurs="1" maxOccurs="1" type="xsd:string">
            <xsd:annotation>
              <xsd:documentation>First name</xsd:documentation>
              <xsd:appinfo xmlns:inf="http://soap.upskills.in/soap/default?services=customerCustomerRepositoryV1">
                <inf:maxLength/>
                <inf:callInfo>
                  <inf:callName>customerCustomerRepositoryV1GetById</inf:callName>
                  <inf:callName>customerCustomerRepositoryV1Save</inf:callName>
                  <inf:returned>Conditionally</inf:returned>
                </inf:callInfo>
                <inf:callInfo>
                  <inf:callName>customerCustomerRepositoryV1Save</inf:callName>
                  <inf:requiredInput>No</inf:requiredInput>
                </inf:callInfo>
              </xsd:appinfo>
            </xsd:annotation>
          </xsd:element>
          <xsd:element name="lastname" minOccurs="1" maxOccurs="1" type="xsd:string">
            <xsd:annotation>
              <xsd:documentation>Last name</xsd:documentation>
              <xsd:appinfo xmlns:inf="http://soap.upskills.in/soap/default?services=customerCustomerRepositoryV1">
                <inf:maxLength/>
                <inf:callInfo>
                  <inf:callName>customerCustomerRepositoryV1GetById</inf:callName>
                  <inf:callName>customerCustomerRepositoryV1Save</inf:callName>
                  <inf:returned>Conditionally</inf:returned>
                </inf:callInfo>
                <inf:callInfo>
                  <inf:callName>customerCustomerRepositoryV1Save</inf:callName>
                  <inf:requiredInput>No</inf:requiredInput>
                </inf:callInfo>
              </xsd:appinfo>
            </xsd:annotation>
          </xsd:element>
          <xsd:element name="middlename" minOccurs="0" maxOccurs="1" type="xsd:string">
            <xsd:annotation>
              <xsd:documentation>Middle name</xsd:documentation>
              <xsd:appinfo xmlns:inf="http://soap.upskills.in/soap/default?services=customerCustomerRepositoryV1">
                <inf:maxLength/>
                <inf:callInfo>
                  <inf:callName>customerCustomerRepositoryV1GetById</inf:callName>
                  <inf:callName>customerCustomerRepositoryV1Save</inf:callName>
                  <inf:returned>Conditionally</inf:returned>
                </inf:callInfo>
                <inf:callInfo>
                  <inf:callName>customerCustomerRepositoryV1Save</inf:callName>
                  <inf:requiredInput>No</inf:requiredInput>
                </inf:callInfo>
              </xsd:appinfo>
            </xsd:annotation>
          </xsd:element>
          <xsd:element name="prefix" minOccurs="0" maxOccurs="1" type="xsd:string">
            <xsd:annotation>
              <xsd:documentation>Prefix</xsd:documentation>
              <xsd:appinfo xmlns:inf="http://soap.upskills.in/soap/default?services=customerCustomerRepositoryV1">
                <inf:maxLength/>
                <inf:callInfo>
                  <inf:callName>customerCustomerRepositoryV1GetById</inf:callName>
                  <inf:callName>customerCustomerRepositoryV1Save</inf:callName>
                  <inf:returned>Conditionally</inf:returned>
                </inf:callInfo>
                <inf:callInfo>
                  <inf:callName>customerCustomerRepositoryV1Save</inf:callName>
                  <inf:requiredInput>No</inf:requiredInput>
                </inf:callInfo>
              </xsd:appinfo>
            </xsd:annotation>
          </xsd:element>
          <xsd:element name="suffix" minOccurs="0" maxOccurs="1" type="xsd:string">
            <xsd:annotation>
              <xsd:documentation>Suffix</xsd:documentation>
              <xsd:appinfo xmlns:inf="http://soap.upskills.in/soap/default?services=customerCustomerRepositoryV1">
                <inf:maxLength/>
                <inf:callInfo>
                  <inf:callName>customerCustomerRepositoryV1GetById</inf:callName>
                  <inf:callName>customerCustomerRepositoryV1Save</inf:callName>
                  <inf:returned>Conditionally</inf:returned>
                </inf:callInfo>
                <inf:callInfo>
                  <inf:callName>customerCustomerRepositoryV1Save</inf:callName>
                  <inf:requiredInput>No</inf:requiredInput>
                </inf:callInfo>
              </xsd:appinfo>
            </xsd:annotation>
          </xsd:element>
          <xsd:element name="gender" minOccurs="0" maxOccurs="1" type="xsd:int">
            <xsd:annotation>
              <xsd:documentation>Gender</xsd:documentation>
              <xsd:appinfo xmlns:inf="http://soap.upskills.in/soap/default?services=customerCustomerRepositoryV1">
                <inf:min/>
                <inf:max/>
                <inf:callInfo>
                  <inf:callName>customerCustomerRepositoryV1GetById</inf:callName>
                  <inf:callName>customerCustomerRepositoryV1Save</inf:callName>
                  <inf:returned>Conditionally</inf:returned>
                </inf:callInfo>
                <inf:callInfo>
                  <inf:callName>customerCustomerRepositoryV1Save</inf:callName>
                  <inf:requiredInput>No</inf:requiredInput>
                </inf:callInfo>
              </xsd:appinfo>
            </xsd:annotation>
          </xsd:element>
          <xsd:element name="storeId" minOccurs="0" maxOccurs="1" type="xsd:int">
            <xsd:annotation>
              <xsd:documentation>Store id</xsd:documentation>
              <xsd:appinfo xmlns:inf="http://soap.upskills.in/soap/default?services=customerCustomerRepositoryV1">
                <inf:min/>
                <inf:max/>
                <inf:callInfo>
                  <inf:callName>customerCustomerRepositoryV1GetById</inf:callName>
                  <inf:callName>customerCustomerRepositoryV1Save</inf:callName>
                  <inf:returned>Conditionally</inf:returned>
                </inf:callInfo>
                <inf:callInfo>
                  <inf:callName>customerCustomerRepositoryV1Save</inf:callName>
                  <inf:requiredInput>No</inf:requiredInput>
                </inf:callInfo>
              </xsd:appinfo>
            </xsd:annotation>
          </xsd:element>
          <xsd:element name="taxvat" minOccurs="0" maxOccurs="1" type="xsd:string">
            <xsd:annotation>
              <xsd:documentation>Tax Vat</xsd:documentation>
              <xsd:appinfo xmlns:inf="http://soap.upskills.in/soap/default?services=customerCustomerRepositoryV1">
                <inf:maxLength/>
                <inf:callInfo>
                  <inf:callName>customerCustomerRepositoryV1GetById</inf:callName>
                  <inf:callName>customerCustomerRepositoryV1Save</inf:callName>
                  <inf:returned>Conditionally</inf:returned>
                </inf:callInfo>
                <inf:callInfo>
                  <inf:callName>customerCustomerRepositoryV1Save</inf:callName>
                  <inf:requiredInput>No</inf:requiredInput>
                </inf:callInfo>
              </xsd:appinfo>
            </xsd:annotation>
          </xsd:element>
          <xsd:element name="websiteId" minOccurs="0" maxOccurs="1" type="xsd:int">
            <xsd:annotation>
              <xsd:documentation>Website id</xsd:documentation>
              <xsd:appinfo xmlns:inf="http://soap.upskills.in/soap/default?services=customerCustomerRepositoryV1">
                <inf:min/>
                <inf:max/>
                <inf:callInfo>
                  <inf:callName>customerCustomerRepositoryV1GetById</inf:callName>
                  <inf:callName>customerCustomerRepositoryV1Save</inf:callName>
                  <inf:returned>Conditionally</inf:returned>
                </inf:callInfo>
                <inf:callInfo>
                  <inf:callName>customerCustomerRepositoryV1Save</inf:callName>
                  <inf:requiredInput>No</inf:requiredInput>
                </inf:callInfo>
              </xsd:appinfo>
            </xsd:annotation>
          </xsd:element>
          <xsd:element name="addresses" type="tns:ArrayOfCustomerDataAddressInterface" minOccurs="0">
            <xsd:annotation>
              <xsd:documentation>Customer addresses.</xsd:documentation>
              <xsd:appinfo xmlns:inf="http://soap.upskills.in/soap/default?services=customerCustomerRepositoryV1">
                <inf:natureOfType>array</inf:natureOfType>
                <inf:callInfo>
                  <inf:callName>customerCustomerRepositoryV1GetById</inf:callName>
                  <inf:callName>customerCustomerRepositoryV1Save</inf:callName>
                  <inf:returned>Conditionally</inf:returned>
                </inf:callInfo>
                <inf:callInfo>
                  <inf:callName>customerCustomerRepositoryV1Save</inf:callName>
                  <inf:requiredInput>No</inf:requiredInput>
                </inf:callInfo>
              </xsd:appinfo>
            </xsd:annotation>
          </xsd:element>
          <xsd:element name="disableAutoGroupChange" minOccurs="0" maxOccurs="1" type="xsd:int">
            <xsd:annotation>
              <xsd:documentation>Disable auto group change flag.</xsd:documentation>
              <xsd:appinfo xmlns:inf="http://soap.upskills.in/soap/default?services=customerCustomerRepositoryV1">
                <inf:min/>
                <inf:max/>
                <inf:callInfo>
                  <inf:callName>customerCustomerRepositoryV1GetById</inf:callName>
                  <inf:callName>customerCustomerRepositoryV1Save</inf:callName>
                  <inf:returned>Conditionally</inf:returned>
                </inf:callInfo>
                <inf:callInfo>
                  <inf:callName>customerCustomerRepositoryV1Save</inf:callName>
                  <inf:requiredInput>No</inf:requiredInput>
                </inf:callInfo>
              </xsd:appinfo>
            </xsd:annotation>
          </xsd:element>
          <xsd:element name="extensionAttributes" minOccurs="0" maxOccurs="1" type="tns:CustomerDataCustomerExtensionInterface">
            <xsd:annotation>
              <xsd:documentation>Existing extension attributes object or create a new one.</xsd:documentation>
              <xsd:appinfo xmlns:inf="http://soap.upskills.in/soap/default?services=customerCustomerRepositoryV1">
                <inf:callInfo>
                  <inf:callName>customerCustomerRepositoryV1GetById</inf:callName>
                  <inf:callName>customerCustomerRepositoryV1Save</inf:callName>
                  <inf:returned>Conditionally</inf:returned>
                </inf:callInfo>
                <inf:callInfo>
                  <inf:callName>customerCustomerRepositoryV1Save</inf:callName>
                  <inf:requiredInput>No</inf:requiredInput>
                </inf:callInfo>
              </xsd:appinfo>
            </xsd:annotation>
          </xsd:element>
          <xsd:element name="customAttributes" type="tns:ArrayOfFrameworkAttributeInterface" minOccurs="0">
            <xsd:annotation>
              <xsd:documentation>Custom attributes values.</xsd:documentation>
              <xsd:appinfo xmlns:inf="http://soap.upskills.in/soap/default?services=customerCustomerRepositoryV1">
                <inf:natureOfType>array</inf:natureOfType>
                <inf:callInfo>
                  <inf:callName>customerCustomerRepositoryV1GetById</inf:callName>
                  <inf:callName>customerCustomerRepositoryV1Save</inf:callName>
                  <inf:returned>Conditionally</inf:returned>
                </inf:callInfo>
                <inf:callInfo>
                  <inf:callName>customerCustomerRepositoryV1Save</inf:callName>
                  <inf:requiredInput>No</inf:requiredInput>
                </inf:callInfo>
              </xsd:appinfo>
            </xsd:annotation>
          </xsd:element>
        </xsd:sequence>
      </xsd:complexType>
      <xsd:complexType name="CustomerCustomerRepositoryV1GetByIdResponse">
        <xsd:annotation>
          <xsd:documentation>Response container for the customerCustomerRepositoryV1GetById call.</xsd:documentation>
          <xsd:appinfo xmlns:inf="http://soap.upskills.in/soap/default?services=customerCustomerRepositoryV1"/>
        </xsd:annotation>
        <xsd:sequence>
          <xsd:element name="result" minOccurs="1" maxOccurs="1" type="tns:CustomerDataCustomerInterface">
            <xsd:annotation>
              <xsd:documentation/>
              <xsd:appinfo xmlns:inf="http://soap.upskills.in/soap/default?services=customerCustomerRepositoryV1">
                <inf:callInfo>
                  <inf:callName>customerCustomerRepositoryV1GetById</inf:callName>
                  <inf:returned>Always</inf:returned>
                </inf:callInfo>
              </xsd:appinfo>
            </xsd:annotation>
          </xsd:element>
        </xsd:sequence>
      </xsd:complexType>
      <xsd:element name="customerCustomerRepositoryV1SaveRequest" type="tns:CustomerCustomerRepositoryV1SaveRequest"/>
      <xsd:complexType name="CustomerCustomerRepositoryV1SaveRequest">
        <xsd:annotation>
          <xsd:documentation>Create or update a customer.</xsd:documentation>
          <xsd:appinfo xmlns:inf="http://soap.upskills.in/soap/default?services=customerCustomerRepositoryV1"/>
        </xsd:annotation>
        <xsd:sequence>
          <xsd:element name="customer" minOccurs="1" maxOccurs="1" type="tns:CustomerDataCustomerInterface">
            <xsd:annotation>
              <xsd:documentation/>
              <xsd:appinfo xmlns:inf="http://soap.upskills.in/soap/default?services=customerCustomerRepositoryV1">
                <inf:callInfo>
                  <inf:callName>customerCustomerRepositoryV1Save</inf:callName>
                  <inf:requiredInput>Yes</inf:requiredInput>
                </inf:callInfo>
              </xsd:appinfo>
            </xsd:annotation>
          </xsd:element>
          <xsd:element name="passwordHash" minOccurs="0" maxOccurs="1" type="xsd:string">
            <xsd:annotation>
              <xsd:documentation/>
              <xsd:appinfo xmlns:inf="http://soap.upskills.in/soap/default?services=customerCustomerRepositoryV1">
                <inf:maxLength/>
                <inf:callInfo>
                  <inf:callName>customerCustomerRepositoryV1Save</inf:callName>
                  <inf:requiredInput>No</inf:requiredInput>
                </inf:callInfo>
              </xsd:appinfo>
            </xsd:annotation>
          </xsd:element>
        </xsd:sequence>
      </xsd:complexType>
      <xsd:element name="customerCustomerRepositoryV1SaveResponse" type="tns:CustomerCustomerRepositoryV1SaveResponse"/>
      <xsd:complexType name="CustomerCustomerRepositoryV1SaveResponse">
        <xsd:annotation>
          <xsd:documentation>Response container for the customerCustomerRepositoryV1Save call.</xsd:documentation>
          <xsd:appinfo xmlns:inf="http://soap.upskills.in/soap/default?services=customerCustomerRepositoryV1"/>
        </xsd:annotation>
        <xsd:sequence>
          <xsd:element name="result" minOccurs="1" maxOccurs="1" type="tns:CustomerDataCustomerInterface">
            <xsd:annotation>
              <xsd:documentation/>
              <xsd:appinfo xmlns:inf="http://soap.upskills.in/soap/default?services=customerCustomerRepositoryV1">
                <inf:callInfo>
                  <inf:callName>customerCustomerRepositoryV1Save</inf:callName>
                  <inf:returned>Always</inf:returned>
                </inf:callInfo>
              </xsd:appinfo>
            </xsd:annotation>
          </xsd:element>
        </xsd:sequence>
      </xsd:complexType>
      <xsd:element name="customerCustomerRepositoryV1GetListRequest" type="tns:CustomerCustomerRepositoryV1GetListRequest"/>
      <xsd:complexType name="FrameworkFilter">
        <xsd:annotation>
          <xsd:documentation>Filter which can be used by any methods from service layer.</xsd:documentation>
          <xsd:appinfo xmlns:inf="http://soap.upskills.in/soap/default?services=customerCustomerRepositoryV1"/>
        </xsd:annotation>
        <xsd:sequence>
          <xsd:element name="field" minOccurs="1" maxOccurs="1" type="xsd:string">
            <xsd:annotation>
              <xsd:documentation>Field</xsd:documentation>
              <xsd:appinfo xmlns:inf="http://soap.upskills.in/soap/default?services=customerCustomerRepositoryV1">
                <inf:maxLength/>
                <inf:callInfo>
                  <inf:callName>customerCustomerRepositoryV1GetList</inf:callName>
                  <inf:requiredInput>No</inf:requiredInput>
                </inf:callInfo>
              </xsd:appinfo>
            </xsd:annotation>
          </xsd:element>
          <xsd:element name="value" minOccurs="1" maxOccurs="1" type="xsd:string">
            <xsd:annotation>
              <xsd:documentation>Value</xsd:documentation>
              <xsd:appinfo xmlns:inf="http://soap.upskills.in/soap/default?services=customerCustomerRepositoryV1">
                <inf:maxLength/>
                <inf:callInfo>
                  <inf:callName>customerCustomerRepositoryV1GetList</inf:callName>
                  <inf:requiredInput>No</inf:requiredInput>
                </inf:callInfo>
              </xsd:appinfo>
            </xsd:annotation>
          </xsd:element>
          <xsd:element name="conditionType" minOccurs="0" maxOccurs="1" type="xsd:string">
            <xsd:annotation>
              <xsd:documentation>Condition type</xsd:documentation>
              <xsd:appinfo xmlns:inf="http://soap.upskills.in/soap/default?services=customerCustomerRepositoryV1">
                <inf:maxLength/>
                <inf:callInfo>
                  <inf:callName>customerCustomerRepositoryV1GetList</inf:callName>
                  <inf:requiredInput>No</inf:requiredInput>
                </inf:callInfo>
              </xsd:appinfo>
            </xsd:annotation>
          </xsd:element>
        </xsd:sequence>
      </xsd:complexType>
      <xsd:complexType name="ArrayOfFrameworkFilter">
        <xsd:annotation>
          <xsd:documentation>An array of FrameworkFilter items.</xsd:documentation>
          <xsd:appinfo xmlns:inf="http://soap.upskills.in/soap/default?services=customerCustomerRepositoryV1"/>
        </xsd:annotation>
        <xsd:sequence>
          <xsd:element name="item" minOccurs="0" maxOccurs="unbounded" type="tns:FrameworkFilter">
            <xsd:annotation>
              <xsd:documentation>An item of ArrayOfFrameworkFilter.</xsd:documentation>
              <xsd:appinfo xmlns:inf="http://soap.upskills.in/soap/default?services=customerCustomerRepositoryV1">
                <inf:callInfo>
                  <inf:callName>customerCustomerRepositoryV1GetList</inf:callName>
                  <inf:requiredInput>No</inf:requiredInput>
                </inf:callInfo>
              </xsd:appinfo>
            </xsd:annotation>
          </xsd:element>
        </xsd:sequence>
      </xsd:complexType>
      <xsd:complexType name="FrameworkSearchFilterGroup">
        <xsd:annotation>
          <xsd:documentation>Groups two or more filters together using a logical OR</xsd:documentation>
          <xsd:appinfo xmlns:inf="http://soap.upskills.in/soap/default?services=customerCustomerRepositoryV1"/>
        </xsd:annotation>
        <xsd:sequence>
          <xsd:element name="filters" type="tns:ArrayOfFrameworkFilter" minOccurs="0">
            <xsd:annotation>
              <xsd:documentation>A list of filters in this group</xsd:documentation>
              <xsd:appinfo xmlns:inf="http://soap.upskills.in/soap/default?services=customerCustomerRepositoryV1">
                <inf:natureOfType>array</inf:natureOfType>
                <inf:callInfo>
                  <inf:callName>customerCustomerRepositoryV1GetList</inf:callName>
                  <inf:requiredInput>No</inf:requiredInput>
                </inf:callInfo>
              </xsd:appinfo>
            </xsd:annotation>
          </xsd:element>
        </xsd:sequence>
      </xsd:complexType>
      <xsd:complexType name="ArrayOfFrameworkSearchFilterGroup">
        <xsd:annotation>
          <xsd:documentation>An array of FrameworkSearchFilterGroup items.</xsd:documentation>
          <xsd:appinfo xmlns:inf="http://soap.upskills.in/soap/default?services=customerCustomerRepositoryV1"/>
        </xsd:annotation>
        <xsd:sequence>
          <xsd:element name="item" minOccurs="0" maxOccurs="unbounded" type="tns:FrameworkSearchFilterGroup">
            <xsd:annotation>
              <xsd:documentation>An item of ArrayOfFrameworkSearchFilterGroup.</xsd:documentation>
              <xsd:appinfo xmlns:inf="http://soap.upskills.in/soap/default?services=customerCustomerRepositoryV1">
                <inf:callInfo>
                  <inf:callName>customerCustomerRepositoryV1GetList</inf:callName>
                  <inf:requiredInput>No</inf:requiredInput>
                </inf:callInfo>
              </xsd:appinfo>
            </xsd:annotation>
          </xsd:element>
        </xsd:sequence>
      </xsd:complexType>
      <xsd:complexType name="FrameworkSortOrder">
        <xsd:annotation>
          <xsd:documentation>Data object for sort order.</xsd:documentation>
          <xsd:appinfo xmlns:inf="http://soap.upskills.in/soap/default?services=customerCustomerRepositoryV1"/>
        </xsd:annotation>
        <xsd:sequence>
          <xsd:element name="field" minOccurs="1" maxOccurs="1" type="xsd:string">
            <xsd:annotation>
              <xsd:documentation>Sorting field.</xsd:documentation>
              <xsd:appinfo xmlns:inf="http://soap.upskills.in/soap/default?services=customerCustomerRepositoryV1">
                <inf:maxLength/>
                <inf:callInfo>
                  <inf:callName>customerCustomerRepositoryV1GetList</inf:callName>
                  <inf:requiredInput>No</inf:requiredInput>
                </inf:callInfo>
              </xsd:appinfo>
            </xsd:annotation>
          </xsd:element>
          <xsd:element name="direction" minOccurs="1" maxOccurs="1" type="xsd:string">
            <xsd:annotation>
              <xsd:documentation>Sorting direction.</xsd:documentation>
              <xsd:appinfo xmlns:inf="http://soap.upskills.in/soap/default?services=customerCustomerRepositoryV1">
                <inf:maxLength/>
                <inf:callInfo>
                  <inf:callName>customerCustomerRepositoryV1GetList</inf:callName>
                  <inf:requiredInput>No</inf:requiredInput>
                </inf:callInfo>
              </xsd:appinfo>
            </xsd:annotation>
          </xsd:element>
        </xsd:sequence>
      </xsd:complexType>
      <xsd:complexType name="ArrayOfFrameworkSortOrder">
        <xsd:annotation>
          <xsd:documentation>An array of FrameworkSortOrder items.</xsd:documentation>
          <xsd:appinfo xmlns:inf="http://soap.upskills.in/soap/default?services=customerCustomerRepositoryV1"/>
        </xsd:annotation>
        <xsd:sequence>
          <xsd:element name="item" minOccurs="0" maxOccurs="unbounded" type="tns:FrameworkSortOrder">
            <xsd:annotation>
              <xsd:documentation>An item of ArrayOfFrameworkSortOrder.</xsd:documentation>
              <xsd:appinfo xmlns:inf="http://soap.upskills.in/soap/default?services=customerCustomerRepositoryV1">
                <inf:callInfo>
                  <inf:callName>customerCustomerRepositoryV1GetList</inf:callName>
                  <inf:requiredInput>No</inf:requiredInput>
                </inf:callInfo>
              </xsd:appinfo>
            </xsd:annotation>
          </xsd:element>
        </xsd:sequence>
      </xsd:complexType>
      <xsd:complexType name="FrameworkSearchCriteriaInterface">
        <xsd:annotation>
          <xsd:documentation>Search criteria interface.</xsd:documentation>
          <xsd:appinfo xmlns:inf="http://soap.upskills.in/soap/default?services=customerCustomerRepositoryV1"/>
        </xsd:annotation>
        <xsd:sequence>
          <xsd:element name="filterGroups" type="tns:ArrayOfFrameworkSearchFilterGroup">
            <xsd:annotation>
              <xsd:documentation>A list of filter groups.</xsd:documentation>
              <xsd:appinfo xmlns:inf="http://soap.upskills.in/soap/default?services=customerCustomerRepositoryV1">
                <inf:natureOfType>array</inf:natureOfType>
                <inf:callInfo>
                  <inf:callName>customerCustomerRepositoryV1GetList</inf:callName>
                  <inf:requiredInput>Yes</inf:requiredInput>
                </inf:callInfo>
              </xsd:appinfo>
            </xsd:annotation>
          </xsd:element>
          <xsd:element name="sortOrders" type="tns:ArrayOfFrameworkSortOrder" minOccurs="0">
            <xsd:annotation>
              <xsd:documentation>Sort order.</xsd:documentation>
              <xsd:appinfo xmlns:inf="http://soap.upskills.in/soap/default?services=customerCustomerRepositoryV1">
                <inf:natureOfType>array</inf:natureOfType>
                <inf:callInfo>
                  <inf:callName>customerCustomerRepositoryV1GetList</inf:callName>
                  <inf:requiredInput>No</inf:requiredInput>
                </inf:callInfo>
              </xsd:appinfo>
            </xsd:annotation>
          </xsd:element>
          <xsd:element name="pageSize" minOccurs="0" maxOccurs="1" type="xsd:int">
            <xsd:annotation>
              <xsd:documentation>Page size.</xsd:documentation>
              <xsd:appinfo xmlns:inf="http://soap.upskills.in/soap/default?services=customerCustomerRepositoryV1">
                <inf:min/>
                <inf:max/>
                <inf:callInfo>
                  <inf:callName>customerCustomerRepositoryV1GetList</inf:callName>
                  <inf:requiredInput>No</inf:requiredInput>
                </inf:callInfo>
              </xsd:appinfo>
            </xsd:annotation>
          </xsd:element>
          <xsd:element name="currentPage" minOccurs="0" maxOccurs="1" type="xsd:int">
            <xsd:annotation>
              <xsd:documentation>Current page.</xsd:documentation>
              <xsd:appinfo xmlns:inf="http://soap.upskills.in/soap/default?services=customerCustomerRepositoryV1">
                <inf:min/>
                <inf:max/>
                <inf:callInfo>
                  <inf:callName>customerCustomerRepositoryV1GetList</inf:callName>
                  <inf:requiredInput>No</inf:requiredInput>
                </inf:callInfo>
              </xsd:appinfo>
            </xsd:annotation>
          </xsd:element>
        </xsd:sequence>
      </xsd:complexType>
      <xsd:complexType name="CustomerCustomerRepositoryV1GetListRequest">
        <xsd:annotation>
          <xsd:documentation>Retrieve customers which match a specified criteria. This call returns an array of objects, but detailed information about each objects attributes might not be included. See https://devdocs.magento.com/codelinks/attributes.html#CustomerRepositoryInterface to determine which call to use to get detailed information about all attributes for an object.</xsd:documentation>
          <xsd:appinfo xmlns:inf="http://soap.upskills.in/soap/default?services=customerCustomerRepositoryV1"/>
        </xsd:annotation>
        <xsd:sequence>
          <xsd:element name="searchCriteria" minOccurs="1" maxOccurs="1" type="tns:FrameworkSearchCriteriaInterface">
            <xsd:annotation>
              <xsd:documentation/>
              <xsd:appinfo xmlns:inf="http://soap.upskills.in/soap/default?services=customerCustomerRepositoryV1">
                <inf:callInfo>
                  <inf:callName>customerCustomerRepositoryV1GetList</inf:callName>
                  <inf:requiredInput>Yes</inf:requiredInput>
                </inf:callInfo>
              </xsd:appinfo>
            </xsd:annotation>
          </xsd:element>
        </xsd:sequence>
      </xsd:complexType>
      <xsd:element name="customerCustomerRepositoryV1GetListResponse" type="tns:CustomerCustomerRepositoryV1GetListResponse"/>
      <xsd:complexType name="ArrayOfCustomerDataCustomerInterface">
        <xsd:annotation>
          <xsd:documentation>An array of CustomerDataCustomerInterface items.</xsd:documentation>
          <xsd:appinfo xmlns:inf="http://soap.upskills.in/soap/default?services=customerCustomerRepositoryV1"/>
        </xsd:annotation>
        <xsd:sequence>
          <xsd:element name="item" minOccurs="0" maxOccurs="unbounded" type="tns:CustomerDataCustomerInterface">
            <xsd:annotation>
              <xsd:documentation>An item of ArrayOfCustomerDataCustomerInterface.</xsd:documentation>
              <xsd:appinfo xmlns:inf="http://soap.upskills.in/soap/default?services=customerCustomerRepositoryV1">
                <inf:callInfo>
                  <inf:callName>customerCustomerRepositoryV1GetList</inf:callName>
                  <inf:returned>Conditionally</inf:returned>
                </inf:callInfo>
              </xsd:appinfo>
            </xsd:annotation>
          </xsd:element>
        </xsd:sequence>
      </xsd:complexType>
      <xsd:complexType name="CustomerDataCustomerSearchResultsInterface">
        <xsd:annotation>
          <xsd:documentation>Interface for customer search results.</xsd:documentation>
          <xsd:appinfo xmlns:inf="http://soap.upskills.in/soap/default?services=customerCustomerRepositoryV1"/>
        </xsd:annotation>
        <xsd:sequence>
          <xsd:element name="items" type="tns:ArrayOfCustomerDataCustomerInterface">
            <xsd:annotation>
              <xsd:documentation>Customers list.</xsd:documentation>
              <xsd:appinfo xmlns:inf="http://soap.upskills.in/soap/default?services=customerCustomerRepositoryV1">
                <inf:natureOfType>array</inf:natureOfType>
                <inf:callInfo>
                  <inf:callName>customerCustomerRepositoryV1GetList</inf:callName>
                  <inf:returned>Always</inf:returned>
                </inf:callInfo>
              </xsd:appinfo>
            </xsd:annotation>
          </xsd:element>
          <xsd:element name="searchCriteria" minOccurs="1" maxOccurs="1" type="tns:FrameworkSearchCriteriaInterface">
            <xsd:annotation>
              <xsd:documentation>Search criteria.</xsd:documentation>
              <xsd:appinfo xmlns:inf="http://soap.upskills.in/soap/default?services=customerCustomerRepositoryV1">
                <inf:callInfo>
                  <inf:callName>customerCustomerRepositoryV1GetList</inf:callName>
                  <inf:returned>Always</inf:returned>
                </inf:callInfo>
              </xsd:appinfo>
            </xsd:annotation>
          </xsd:element>
          <xsd:element name="totalCount" minOccurs="1" maxOccurs="1" type="xsd:int">
            <xsd:annotation>
              <xsd:documentation>Total count.</xsd:documentation>
              <xsd:appinfo xmlns:inf="http://soap.upskills.in/soap/default?services=customerCustomerRepositoryV1">
                <inf:min/>
                <inf:max/>
                <inf:callInfo>
                  <inf:callName>customerCustomerRepositoryV1GetList</inf:callName>
                  <inf:returned>Always</inf:returned>
                </inf:callInfo>
              </xsd:appinfo>
            </xsd:annotation>
          </xsd:element>
        </xsd:sequence>
      </xsd:complexType>
      <xsd:complexType name="CustomerCustomerRepositoryV1GetListResponse">
        <xsd:annotation>
          <xsd:documentation>Response container for the customerCustomerRepositoryV1GetList call.</xsd:documentation>
          <xsd:appinfo xmlns:inf="http://soap.upskills.in/soap/default?services=customerCustomerRepositoryV1"/>
        </xsd:annotation>
        <xsd:sequence>
          <xsd:element name="result" minOccurs="1" maxOccurs="1" type="tns:CustomerDataCustomerSearchResultsInterface">
            <xsd:annotation>
              <xsd:documentation/>
              <xsd:appinfo xmlns:inf="http://soap.upskills.in/soap/default?services=customerCustomerRepositoryV1">
                <inf:callInfo>
                  <inf:callName>customerCustomerRepositoryV1GetList</inf:callName>
                  <inf:returned>Always</inf:returned>
                </inf:callInfo>
              </xsd:appinfo>
            </xsd:annotation>
          </xsd:element>
        </xsd:sequence>
      </xsd:complexType>
      <xsd:element name="customerCustomerRepositoryV1DeleteByIdRequest" type="tns:CustomerCustomerRepositoryV1DeleteByIdRequest"/>
      <xsd:complexType name="CustomerCustomerRepositoryV1DeleteByIdRequest">
        <xsd:annotation>
          <xsd:documentation>Delete customer by Customer ID.</xsd:documentation>
          <xsd:appinfo xmlns:inf="http://soap.upskills.in/soap/default?services=customerCustomerRepositoryV1"/>
        </xsd:annotation>
        <xsd:sequence>
          <xsd:element name="customerId" minOccurs="1" maxOccurs="1" type="xsd:int">
            <xsd:annotation>
              <xsd:documentation/>
              <xsd:appinfo xmlns:inf="http://soap.upskills.in/soap/default?services=customerCustomerRepositoryV1">
                <inf:min/>
                <inf:max/>
                <inf:callInfo>
                  <inf:callName>customerCustomerRepositoryV1DeleteById</inf:callName>
                  <inf:requiredInput>Yes</inf:requiredInput>
                </inf:callInfo>
              </xsd:appinfo>
            </xsd:annotation>
          </xsd:element>
        </xsd:sequence>
      </xsd:complexType>
      <xsd:element name="customerCustomerRepositoryV1DeleteByIdResponse" type="tns:CustomerCustomerRepositoryV1DeleteByIdResponse"/>
      <xsd:complexType name="CustomerCustomerRepositoryV1DeleteByIdResponse">
        <xsd:annotation>
          <xsd:documentation>Response container for the customerCustomerRepositoryV1DeleteById call.</xsd:documentation>
          <xsd:appinfo xmlns:inf="http://soap.upskills.in/soap/default?services=customerCustomerRepositoryV1"/>
        </xsd:annotation>
        <xsd:sequence>
          <xsd:element name="result" minOccurs="1" maxOccurs="1" type="xsd:boolean">
            <xsd:annotation>
              <xsd:documentation>true on success</xsd:documentation>
              <xsd:appinfo xmlns:inf="http://soap.upskills.in/soap/default?services=customerCustomerRepositoryV1">
                <inf:default>false</inf:default>
                <inf:callInfo>
                  <inf:callName>customerCustomerRepositoryV1DeleteById</inf:callName>
                  <inf:returned>Always</inf:returned>
                </inf:callInfo>
              </xsd:appinfo>
            </xsd:annotation>
          </xsd:element>
        </xsd:sequence>
      </xsd:complexType>
    </xsd:schema>
  </types>
  <message name="GenericFault">
    <part name="messageParameters" element="tns:GenericFault"/>
  </message>
  <portType name="customerCustomerRepositoryV1PortType">
    <operation name="customerCustomerRepositoryV1GetById">
      <input message="tns:customerCustomerRepositoryV1GetByIdRequest"/>
      <output message="tns:customerCustomerRepositoryV1GetByIdResponse"/>
      <fault name="GenericFault" message="tns:GenericFault"/>
    </operation>
    <operation name="customerCustomerRepositoryV1Save">
      <input message="tns:customerCustomerRepositoryV1SaveRequest"/>
      <output message="tns:customerCustomerRepositoryV1SaveResponse"/>
      <fault name="GenericFault" message="tns:GenericFault"/>
    </operation>
    <operation name="customerCustomerRepositoryV1GetList">
      <input message="tns:customerCustomerRepositoryV1GetListRequest"/>
      <output message="tns:customerCustomerRepositoryV1GetListResponse"/>
      <fault name="GenericFault" message="tns:GenericFault"/>
    </operation>
    <operation name="customerCustomerRepositoryV1DeleteById">
      <input message="tns:customerCustomerRepositoryV1DeleteByIdRequest"/>
      <output message="tns:customerCustomerRepositoryV1DeleteByIdResponse"/>
      <fault name="GenericFault" message="tns:GenericFault"/>
    </operation>
  </portType>
  <binding name="customerCustomerRepositoryV1Binding" type="tns:customerCustomerRepositoryV1PortType">
    <soap12:binding style="document" transport="http://schemas.xmlsoap.org/soap/http"/>
    <operation name="customerCustomerRepositoryV1GetById">
      <soap12:operation soapAction="customerCustomerRepositoryV1GetById"/>
      <input>
        <soap12:body use="literal"/>
      </input>
      <output>
        <soap12:body use="literal"/>
      </output>
      <fault name="GenericFault"/>
    </operation>
    <operation name="customerCustomerRepositoryV1Save">
      <soap12:operation soapAction="customerCustomerRepositoryV1Save"/>
      <input>
        <soap12:body use="literal"/>
      </input>
      <output>
        <soap12:body use="literal"/>
      </output>
      <fault name="GenericFault"/>
    </operation>
    <operation name="customerCustomerRepositoryV1GetList">
      <soap12:operation soapAction="customerCustomerRepositoryV1GetList"/>
      <input>
        <soap12:body use="literal"/>
      </input>
      <output>
        <soap12:body use="literal"/>
      </output>
      <fault name="GenericFault"/>
    </operation>
    <operation name="customerCustomerRepositoryV1DeleteById">
      <soap12:operation soapAction="customerCustomerRepositoryV1DeleteById"/>
      <input>
        <soap12:body use="literal"/>
      </input>
      <output>
        <soap12:body use="literal"/>
      </output>
      <fault name="GenericFault"/>
    </operation>
  </binding>
  <service name="customerCustomerRepositoryV1Service">
    <port name="customerCustomerRepositoryV1Port" binding="tns:customerCustomerRepositoryV1Binding">
      <soap12:address location="http://soap.upskills.in/soap/default?services=customerCustomerRepositoryV1"/>
    </port>
  </service>
  <message name="customerCustomerRepositoryV1GetByIdRequest">
    <part name="messageParameters" element="tns:customerCustomerRepositoryV1GetByIdRequest"/>
  </message>
  <message name="customerCustomerRepositoryV1GetByIdResponse">
    <part name="messageParameters" element="tns:customerCustomerRepositoryV1GetByIdResponse"/>
  </message>
  <message name="customerCustomerRepositoryV1SaveRequest">
    <part name="messageParameters" element="tns:customerCustomerRepositoryV1SaveRequest"/>
  </message>
  <message name="customerCustomerRepositoryV1SaveResponse">
    <part name="messageParameters" element="tns:customerCustomerRepositoryV1SaveResponse"/>
  </message>
  <message name="customerCustomerRepositoryV1GetListRequest">
    <part name="messageParameters" element="tns:customerCustomerRepositoryV1GetListRequest"/>
  </message>
  <message name="customerCustomerRepositoryV1GetListResponse">
    <part name="messageParameters" element="tns:customerCustomerRepositoryV1GetListResponse"/>
  </message>
  <message name="customerCustomerRepositoryV1DeleteByIdRequest">
    <part name="messageParameters" element="tns:customerCustomerRepositoryV1DeleteByIdRequest"/>
  </message>
  <message name="customerCustomerRepositoryV1DeleteByIdResponse">
    <part name="messageParameters" element="tns:customerCustomerRepositoryV1DeleteByIdResponse"/>
  </message>
</definitions>]]></con:content><con:type>http://schemas.xmlsoap.org/wsdl/</con:type></con:part></con:definitionCache><con:endpoints><con:endpoint>http://soap.upskills.in/soap/default?services=customerCustomerRepositoryV1</con:endpoint></con:endpoints><con:operation id="463c5e89-e337-4c71-a868-db1a068f94bd" isOneWay="false" action="customerCustomerRepositoryV1DeleteById" name="customerCustomerRepositoryV1DeleteById" bindingOperationName="customerCustomerRepositoryV1DeleteById" type="Request-Response" inputName="" receivesAttachments="false" sendsAttachments="false" anonymous="optional"><con:settings/><con:call id="393e78ba-5947-4cc9-b419-b12d22632251" name="Request 1"><con:settings/><con:encoding>UTF-8</con:encoding><con:endpoint>http://soap.upskills.in/soap/default?services=customerCustomerRepositoryV1</con:endpoint><con:request><![CDATA[<soap:Envelope xmlns:soap="http://www.w3.org/2003/05/soap-envelope" xmlns:def="http://soap.upskills.in/soap/default?services=customerCustomerRepositoryV1">\r
   <soap:Header/>\r
   <soap:Body>\r
      <def:customerCustomerRepositoryV1DeleteByIdRequest>\r
         <customerId>?</customerId>\r
      </def:customerCustomerRepositoryV1DeleteByIdRequest>\r
   </soap:Body>\r
</soap:Envelope>]]></con:request><con:credentials><con:authType>No Authorization</con:authType></con:credentials><con:jmsConfig JMSDeliveryMode="PERSISTENT"/><con:jmsPropertyConfig/><con:wsaConfig mustUnderstand="NONE" version="200508" action="http://soap.upskills.in/soap/default?services=customerCustomerRepositoryV1/customerCustomerRepositoryV1PortType/customerCustomerRepositoryV1DeleteByIdRequest"/><con:wsrmConfig version="1.2"/></con:call></con:operation><con:operation id="6a145812-b076-4daf-a1c5-3b038994829f" isOneWay="false" action="customerCustomerRepositoryV1GetById" name="customerCustomerRepositoryV1GetById" bindingOperationName="customerCustomerRepositoryV1GetById" type="Request-Response" inputName="" receivesAttachments="false" sendsAttachments="false" anonymous="optional"><con:settings/><con:call id="e30adc5e-1d27-4982-80e5-af28d75b18da" name="Request 1"><con:settings/><con:encoding>UTF-8</con:encoding><con:endpoint>http://soap.upskills.in/soap/default?services=customerCustomerRepositoryV1</con:endpoint><con:request><![CDATA[<soap:Envelope xmlns:soap="http://www.w3.org/2003/05/soap-envelope" xmlns:def="http://soap.upskills.in/soap/default?services=customerCustomerRepositoryV1">\r
   <soap:Header/>\r
   <soap:Body>\r
      <def:customerCustomerRepositoryV1GetByIdRequest>\r
         <customerId>?</customerId>\r
      </def:customerCustomerRepositoryV1GetByIdRequest>\r
   </soap:Body>\r
</soap:Envelope>]]></con:request><con:wsaConfig mustUnderstand="NONE" version="200508" action="http://soap.upskills.in/soap/default?services=customerCustomerRepositoryV1/customerCustomerRepositoryV1PortType/customerCustomerRepositoryV1GetByIdRequest"/></con:call></con:operation><con:operation id="bbed800e-9180-4bb1-b7c7-fe4838f6d220" isOneWay="false" action="customerCustomerRepositoryV1GetList" name="customerCustomerRepositoryV1GetList" bindingOperationName="customerCustomerRepositoryV1GetList" type="Request-Response" inputName="" receivesAttachments="false" sendsAttachments="false" anonymous="optional"><con:settings/><con:call id="fdc55e65-8134-4697-8d68-cb548e183c0b" name="Request 1"><con:settings/><con:encoding>UTF-8</con:encoding><con:endpoint>http://soap.upskills.in/soap/default?services=customerCustomerRepositoryV1</con:endpoint><con:request><![CDATA[<soap:Envelope xmlns:soap="http://www.w3.org/2003/05/soap-envelope" xmlns:def="http://soap.upskills.in/soap/default?services=customerCustomerRepositoryV1">\r
   <soap:Header/>\r
   <soap:Body>\r
      <def:customerCustomerRepositoryV1GetListRequest>\r
         <searchCriteria>\r
            <filterGroups>\r
               <!--Zero or more repetitions:-->\r
               <item>\r
                  <!--Optional:-->\r
                  <filters>\r
                     <!--Zero or more repetitions:-->\r
                     <item>\r
                        <field>?</field>\r
                        <value>?</value>\r
                        <!--Optional:-->\r
                        <conditionType>?</conditionType>\r
                     </item>\r
                  </filters>\r
               </item>\r
            </filterGroups>\r
            <!--Optional:-->\r
            <sortOrders>\r
               <!--Zero or more repetitions:-->\r
               <item>\r
                  <field>?</field>\r
                  <direction>?</direction>\r
               </item>\r
            </sortOrders>\r
            <!--Optional:-->\r
            <pageSize>?</pageSize>\r
            <!--Optional:-->\r
            <currentPage>?</currentPage>\r
         </searchCriteria>\r
      </def:customerCustomerRepositoryV1GetListRequest>\r
   </soap:Body>\r
</soap:Envelope>]]></con:request><con:credentials><con:authType>No Authorization</con:authType></con:credentials><con:jmsConfig JMSDeliveryMode="PERSISTENT"/><con:jmsPropertyConfig/><con:wsaConfig mustUnderstand="NONE" version="200508" action="http://soap.upskills.in/soap/default?services=customerCustomerRepositoryV1/customerCustomerRepositoryV1PortType/customerCustomerRepositoryV1GetListRequest"/><con:wsrmConfig version="1.2"/></con:call></con:operation><con:operation id="042a8610-584d-45d4-9a56-b6c790e61823" isOneWay="false" action="customerCustomerRepositoryV1Save" name="customerCustomerRepositoryV1Save" bindingOperationName="customerCustomerRepositoryV1Save" type="Request-Response" inputName="" receivesAttachments="false" sendsAttachments="false" anonymous="optional"><con:settings/><con:call id="6eade38d-1863-4c95-92a8-10985eba18ae" name="Request 1"><con:settings><con:setting id="com.eviware.soapui.impl.wsdl.WsdlRequest@request-headers">&lt;xml-fragment/></con:setting></con:settings><con:encoding>UTF-8</con:encoding><con:endpoint>http://soap.upskills.in/soap/default?services=customerCustomerRepositoryV1</con:endpoint><con:request><![CDATA[<email>rahulp.mit@gmail.com</email>
<firstname>Rahul</firstname>
<lastname>Poddar</lastname>
<dob>2020-11-24</dob>
<addresses>
   <item>
      <region>
         <regionCode>KA</regionCode>
         <region>Karnataka</region>
      </region>
      <countryId>IN</countryId>
      <street>
         <item>#55, 1 st Main Road</item>
      </street>
      <telephone>+91 9876543210</telephone>
      <postcode>560023</postcode>
      <city>Bengaluru</city>
      <firstname>Krishna</firstname>
      <lastname>Mohan</lastname>
      <defaultShipping>true</defaultShipping>
      <defaultBilling>true</defaultBilling>
   </item>
</addresses>]]></con:request><con:credentials><con:authType>No Authorization</con:authType></con:credentials><con:jmsConfig JMSDeliveryMode="PERSISTENT"/><con:jmsPropertyConfig/><con:wsaConfig mustUnderstand="NONE" version="200508" action="http://soap.upskills.in/soap/default?services=customerCustomerRepositoryV1/customerCustomerRepositoryV1PortType/customerCustomerRepositoryV1SaveRequest"/><con:wsrmConfig version="1.2"/></con:call></con:operation></con:interface><con:testSuite id="025bac29-bfa0-49fb-94b6-2eac8697eb58" name="GetCustomer"><con:settings/><con:runType>SEQUENTIAL</con:runType><con:testCase id="46a7b587-edf5-4877-b18c-53e0c8fc73cd" failOnError="true" failTestCaseOnErrors="true" keepSession="false" maxResults="0" name="TC01" searchProperties="true"><con:settings/><con:testStep type="properties" name="Property" id="5b2abcf7-1970-49f4-9af6-b9b07d20f82c"><con:settings/><con:config xsi:type="con:PropertiesStep" saveFirst="true" xmlns:xsi="http://www.w3.org/2001/XMLSchema-instance"><con:properties><con:property><con:name>name</con:name><con:value>Anand</con:value></con:property><con:property><con:name>lastname</con:name><con:value>Lucknow12</con:value></con:property><con:property><con:name>email</con:name><con:value>anand@gmail.com</con:value></con:property></con:properties></con:config></con:testStep><con:testStep type="request" name="saveCustomer" id="8646395f-fca2-4338-b0c1-0e8486b79fac"><con:settings/><con:config xsi:type="con:RequestStep" xmlns:xsi="http://www.w3.org/2001/XMLSchema-instance"><con:interface>customerCustomerRepositoryV1Binding</con:interface><con:operation>customerCustomerRepositoryV1Save</con:operation><con:request name="saveCustomer" id="7fdde042-cee8-4c79-a66a-bd03b4eadfb9"><con:settings><con:setting id="com.eviware.soapui.impl.wsdl.WsdlRequest@request-headers">&lt;entry key="Authorization" value="bearer ${#TestCase#token}" xmlns="http://eviware.com/soapui/config"/></con:setting></con:settings><con:encoding>UTF-8</con:encoding><con:endpoint>http://soap.upskills.in/soap/default?services=customerCustomerRepositoryV1</con:endpoint><con:request><![CDATA[<soap:Envelope xmlns:soap="http://www.w3.org/2003/05/soap-envelope" xmlns:def="http://soap.upskills.in/soap/default?services=customerCustomerRepositoryV1">\r
   <soap:Header/>\r
   <soap:Body>\r
      <def:customerCustomerRepositoryV1SaveRequest>\r
         <customer>\r
            <email>rahulp.mit@gmail.com</email>\r
            <firstname>Rahul</firstname>\r
            <lastname>Poddar</lastname>\r
         </customer>\r
      </def:customerCustomerRepositoryV1SaveRequest>\r
   </soap:Body>\r
</soap:Envelope>]]></con:request><con:assertion type="SOAP Response" id="1f8409b3-63c5-45aa-a357-f11777f05841"/><con:assertion type="GroovyScriptAssertion" id="30a3719b-a8f9-4dad-b8d2-e25b525e416a" name="Script Assertion"><con:configuration><scriptText>import com.eviware.soapui.support.XmlHolder

def res=context.testCase.getTestStepByName('saveCustomer').getPropertyValue("Response")

log.info res

def holder=new XmlHolder(res)
def result=holder.getNodeValue("//*:id")
context.testCase.setPropertyValue("id",result)

log.info "Customer_id is "+result</scriptText></con:configuration></con:assertion><con:credentials><con:authType>No Authorization</con:authType></con:credentials><con:jmsConfig JMSDeliveryMode="PERSISTENT"/><con:jmsPropertyConfig/><con:wsaConfig mustUnderstand="NONE" version="200508"/><con:wsrmConfig version="1.2"/></con:request></con:config></con:testStep><con:testStep type="request" name="getList" id="1b8467bf-0196-45a6-b1d3-997e61a1e583"><con:settings/><con:config xsi:type="con:RequestStep" xmlns:xsi="http://www.w3.org/2001/XMLSchema-instance"><con:interface>customerCustomerRepositoryV1Binding</con:interface><con:operation>customerCustomerRepositoryV1GetList</con:operation><con:request name="getList" id="cb610441-b445-4a65-b7f3-c104e98e09f4"><con:settings><con:setting id="com.eviware.soapui.impl.wsdl.WsdlRequest@request-headers">&lt;entry key="Authorization" value="bearer ${#TestCase#token}" xmlns="http://eviware.com/soapui/config"/></con:setting></con:settings><con:encoding>UTF-8</con:encoding><con:endpoint>http://soap.upskills.in/soap/default?services=customerCustomerRepositoryV1</con:endpoint><con:request><![CDATA[<soap:Envelope xmlns:soap="http://www.w3.org/2003/05/soap-envelope" xmlns:def="http://soap.upskills.in/soap/default?services=customerCustomerRepositoryV1">\r
   <soap:Header/>\r
   <soap:Body>\r
      <def:customerCustomerRepositoryV1GetListRequest>\r
         <searchCriteria>\r
            <filterGroups/>\r
         </searchCriteria>\r
      </def:customerCustomerRepositoryV1GetListRequest>\r
   </soap:Body>\r
</soap:Envelope>]]></con:request><con:assertion type="SOAP Response" id="beb18dd1-a964-4603-b8d0-47c19c9d3b02"/><con:assertion type="GroovyScriptAssertion" id="03bea8e7-b9fd-45f6-b7e2-b2ba0db39942" name="Script Assertion"><con:configuration><scriptText>import com.eviware.soapui.support.XmlHolder

def res=context.testCase.getTestStepByName('getList').getPropertyValue("Response")

log.info res

log.info "GetList passed"</scriptText></con:configuration></con:assertion><con:credentials><con:authType>No Authorization</con:authType></con:credentials><con:jmsConfig JMSDeliveryMode="PERSISTENT"/><con:jmsPropertyConfig/><con:wsaConfig mustUnderstand="NONE" version="200508"/><con:wsrmConfig version="1.2"/></con:request></con:config></con:testStep><con:testStep type="request" name="getById" id="86ce81c7-9dc7-4c37-a30d-844bddb2aa69"><con:settings/><con:config xsi:type="con:RequestStep" xmlns:xsi="http://www.w3.org/2001/XMLSchema-instance"><con:interface>customerCustomerRepositoryV1Binding</con:interface><con:operation>customerCustomerRepositoryV1GetById</con:operation><con:request name="getById" id="03977c70-c021-4b5d-9220-32803fce5997"><con:settings><con:setting id="com.eviware.soapui.impl.wsdl.WsdlRequest@request-headers">&lt;entry key="Authorization" value="bearer ${#TestCase#token}" xmlns="http://eviware.com/soapui/config"/></con:setting></con:settings><con:encoding>UTF-8</con:encoding><con:endpoint>http://soap.upskills.in/soap/default?services=customerCustomerRepositoryV1</con:endpoint><con:request><![CDATA[<soap:Envelope xmlns:soap="http://www.w3.org/2003/05/soap-envelope" xmlns:def="http://soap.upskills.in/soap/default?services=customerCustomerRepositoryV1">\r
   <soap:Header/>\r
   <soap:Body>\r
      <def:customerCustomerRepositoryV1GetByIdRequest>\r
         <customerId>${#TestCase#id}</customerId>\r
      </def:customerCustomerRepositoryV1GetByIdRequest>\r
   </soap:Body>\r
</soap:Envelope>]]></con:request><con:assertion type="SOAP Response" id="b5751463-8a34-4892-82d6-3d2a20e0646f"/><con:assertion type="Simple Contains" id="c3ede18c-3028-42a8-9585-4fa7474b3982" name="Contains"><con:configuration><token>false</token><ignoreCase>false</ignoreCase><useRegEx>false</useRegEx></con:configuration></con:assertion><con:credentials><con:authType>No Authorization</con:authType></con:credentials><con:jmsConfig JMSDeliveryMode="PERSISTENT"/><con:jmsPropertyConfig/><con:wsaConfig mustUnderstand="NONE" version="200508"/><con:wsrmConfig version="1.2"/></con:request></con:config></con:testStep><con:testStep type="request" name="deleteId" id="32bb2d80-9e09-4fa9-8244-1114d6608b90"><con:settings/><con:config xsi:type="con:RequestStep" xmlns:xsi="http://www.w3.org/2001/XMLSchema-instance"><con:interface>customerCustomerRepositoryV1Binding</con:interface><con:operation>customerCustomerRepositoryV1DeleteById</con:operation><con:request name="deleteId" id="03d509e1-3b79-4f3d-822a-9736c5c0b45c"><con:settings><con:setting id="com.eviware.soapui.impl.wsdl.WsdlRequest@request-headers">&lt;entry key="Authorization" value="bearer ${#TestCase#token}" xmlns="http://eviware.com/soapui/config"/></con:setting></con:settings><con:encoding>UTF-8</con:encoding><con:endpoint>http://soap.upskills.in/soap/default?services=customerCustomerRepositoryV1</con:endpoint><con:request><![CDATA[<soap:Envelope xmlns:soap="http://www.w3.org/2003/05/soap-envelope" xmlns:def="http://soap.upskills.in/soap/default?services=customerCustomerRepositoryV1">\r
   <soap:Header/>\r
   <soap:Body>\r
      <def:customerCustomerRepositoryV1DeleteByIdRequest>\r
         <customerId>${#TestCase#id}</customerId>\r
      </def:customerCustomerRepositoryV1DeleteByIdRequest>\r
   </soap:Body>\r
</soap:Envelope>]]></con:request><con:assertion type="SOAP Response" id="3a74cb7f-a85c-4336-9e24-7f69f5f86411"/><con:assertion type="Simple Contains" id="2defd1fb-8eaa-47c8-a64a-383c62b823de" name="Contains"><con:configuration><token>true</token><ignoreCase>false</ignoreCase><useRegEx>false</useRegEx></con:configuration></con:assertion><con:credentials><con:authType>No Authorization</con:authType></con:credentials><con:jmsConfig JMSDeliveryMode="PERSISTENT"/><con:jmsPropertyConfig/><con:wsaConfig mustUnderstand="NONE" version="200508"/><con:wsrmConfig version="1.2"/></con:request></con:config></con:testStep><con:properties><con:property><con:name>token</con:name><con:value>f0rf13pxtxp7mftwc23rq6e52yvmi5um</con:value></con:property><con:property><con:name>id</con:name><con:value>3324</con:value></con:property></con:properties></con:testCase><con:testCase id="2e924234-1949-4f85-8ac2-b07fae412d1a" failOnError="true" failTestCaseOnErrors="true" keepSession="false" maxResults="0" name="TestCase" searchProperties="true"><con:settings/><con:testStep type="groovy" name="Groovy Script" id="487cba4a-66f6-4556-895c-475a347e0172"><con:settings/><con:config><script>import jxl.*
def username,lastname,email

String filepath="C:/Users/RahulPoddar/Desktop/SDET/SampleData1.xls"
File Excel=new File(filepath)

Workbook wb=Workbook.getWorkbook(Excel)
Sheet sh=wb.getSheet("Sheet1")

def rowsize=sh.getRows();
def columnsize=sh.getColumns();

log.info rowsize
log.info columnsize

for (def i=0;i&lt;rowsize;i++)
{
	for (def j=0;j&lt;columnsize;j++)
	{
		if (j==0)
		{
			username=sh.getCell(j,i).getContents();
		}
		if (j==1)
		{
			lastname=sh.getCell(j,i).getContents();
		}
		else{
			email=sh.getCell(j,i).getContents();
		}
	}
	def tc=testRunner.testCase.testSuite.project.testSuites['GetCustomer'].testCases['TC01']
	tc.testSteps['Property'].setPropertyValue("name",username)
	tc.testSteps['Property'].setPropertyValue("lastname",lastname)
	tc.testSteps['Property'].setPropertyValue("email",email)
	log.info "Username is "+username
	log.info "Lastname is "+lastname
	log.info "Email is "+email
	
	def runner=tc.run(null,false)
	log.info "Total no. of steps are "+runner.results.size()
}
</script></con:config></con:testStep><con:properties/></con:testCase><con:properties/></con:testSuite><con:properties/><con:wssContainer/><con:oAuth2ProfileContainer/><con:oAuth1ProfileContainer/><con:sensitiveInformation/></con:soapui-project>